Workbook
Name v_revenue: '1) Data Entry Logic'!$I$8
Name v_contracts: '1) Data Entry Logic'!$I$9
Name v_cost_of_revenue_amt: '1) Data Entry Logic'!$I$10
Name v_cost_of_revenue_pct: '1) Data Entry Logic'!$I$11
Name v_rnd_amt: '1) Data Entry Logic'!$I$12
Name v_rnd_pct: '1) Data Entry Logic'!$I$13
Name v_gna_amt: '1) Data Entry Logic'!$I$14
Name v_gna_pct: '1) Data Entry Logic'!$I$15
Name v_base_salary: '1) Data Entry Logic'!$I$16
Name v_load_rate: '1) Data Entry Logic'!$I$17
Name v_loaded_salary: '1) Data Entry Logic'!$I$18
Name v_trip_fare: '1) Data Entry Logic'!$I$19
Name v_trip_ground: '1) Data Entry Logic'!$I$20
Name v_trip_meals: '1) Data Entry Logic'!$I$21
Name v_trip_lodging: '1) Data Entry Logic'!$I$22
Name v_trip_days: '1) Data Entry Logic'!$I$23
Name v_trip_entertainment: '1) Data Entry Logic'!$I$24
Name v_trips_per_year: '1) Data Entry Logic'!$I$25
Name v_travel_per_salesperson: '1) Data Entry Logic'!$I$26
Name v_commissions_paid: '1) Data Entry Logic'!$I$27
Name v_commission_rate: '1) Data Entry Logic'!$I$28
Name v_oh_managers: '1) Data Entry Logic'!$I$29
Name v_oh_engineers: '1) Data Entry Logic'!$I$30
Name v_oh_admin: '1) Data Entry Logic'!$I$31
Name v_oh_training: '1) Data Entry Logic'!$I$32
Name v_oh_incentives: '1) Data Entry Logic'!$I$33
Name v_sales_overhead: '1) Data Entry Logic'!$I$34
Name v_mk_people: '1) Data Entry Logic'!$I$35
Name v_mk_web: '1) Data Entry Logic'!$I$36
Name v_mk_events: '1) Data Entry Logic'!$I$37
Name v_mk_ads: '1) Data Entry Logic'!$I$38
Name v_mk_mail: '1) Data Entry Logic'!$I$39
Name v_mk_leadgen: '1) Data Entry Logic'!$I$40
Name v_mk_brand: '1) Data Entry Logic'!$I$41
Name v_mk_collateral: '1) Data Entry Logic'!$I$42
Name v_marketing: '1) Data Entry Logic'!$I$43
Name v_territory_count: '1) Data Entry Logic'!$I$44
Name v_open_territories: '1) Data Entry Logic'!$I$45
Name v_filled_seats: '1) Data Entry Logic'!$I$46
Name v_ramp_months: '1) Data Entry Logic'!$I$47
Name v_opps_won: '1) Data Entry Logic'!$I$48
Name v_opps_lost: '1) Data Entry Logic'!$I$49
Name v_win_rate: '1) Data Entry Logic'!$I$50
Name v_cycle_months: '1) Data Entry Logic'!$I$51
Name v_deal_size: '1) Data Entry Logic'!$I$52
Name v_open_opps_total: '1) Data Entry Logic'!$I$53
Name v_opportunities_capacity: '1) Data Entry Logic'!$I$54
Name st_required: '1) Data Entry Logic'!$C$70
Name st_validated: '1) Data Entry Logic'!$C$71
Name st_review: '1) Data Entry Logic'!$C$72
Name v_banner: '1) Data Entry Logic'!$C$73
Name m_base_revenue: '2) What-If Logic'!$C$25
Name m_base_contracts: '2) What-If Logic'!$C$23
Name wi_select: '2) What-If'!$C$7
Name wi_win: '2) What-If'!$C$8
Name wi_cycle: '2) What-If'!$C$9
Name wi_deal: '2) What-If'!$C$10
Name wi_target: '2) What-If'!$C$11

Sheet Orientation
B2: Commercial Effectiveness Model
B3: © 2000–2026 Growth Enablement. All rights reserved.
B6: What this model does
B7: This model describes how your commercial system works, tests that description against your actual financial results, and then lets you explore what would happen if you changed it.
B8: It is built on one discipline: lead with your assumptions. Every number you enter is a claim about your business. The model asks where each claim comes from, checks it against your other numbers, and shows which results rest on validated actuals and which on estimates. If anyone disagrees with a result, you can go straight back to the assumption behind it.
B10: How the model sees sales capacity
B11: • Territories are a design choice. You decide how to divide your market and how many territories to fund. A territory without a salesperson still carries an expected yield, so leaving it open has a cost.
B12: • Salespeople are a hiring choice. A salesperson's capacity is not the hours they work. It is how many opportunities they can hold and advance well at the same time, turned over by the length of your sales cycle.
B13: • Revenue = salespeople × opportunities worked at once × (12 ÷ cycle months) × close rate × deal size. Every cost then flows through a pro forma income statement to operating income.
B15: How the workbook is organized
B16: Each tab has two worksheets. The client view holds only what you enter or choose, and the results. The logic sheet shows every calculation, one per row, with the rule written in words next to the live formula, so anyone can audit how a result was produced.
B17: Worksheet | C17: Who uses it | D17: What it holds
B18: 1) Data Entry | C18: Client: Finance, Sales Operations, HR | D18: Four steps, in the order the data is easiest to collect. For each entry: your value and where it came from. Shows the value the model uses and the cross-checks.
B19: 1) Data Entry Logic | C19: Growth Enablement and Finance reviewers | D19: For each entry: the rule that picks the value used, our estimate and how it is calculated, the default, and the basis. The cross-check calculations.
B20: 2) What-If | C20: Client: leadership | D20: Choose a scenario and the size of each improvement. Shows the pro forma income statement, the four scenarios side by side, and what it would take to reach a target operating income.
B21: 2) What-If Logic | C21: Growth Enablement and Finance reviewers | D21: Baseline and the four scenarios, calculated step by step from salesperson capacity to operating income, with a true-up.
B23: How to use it
B24: 1. Collect the data (1) Data Entry). Work through the four steps in order; each names who usually owns the data, so the sheet can be forwarded. For each entry, type your value and choose its source:
B25: – Validated by Finance: confirmed by your Finance team from your records.
B26: – Your entry: your best number, not yet validated. Accepted, but labeled.
B27: – Use our estimate: the model calculates it from your other entries (for example, revenue ÷ contracts).
B28: – Left blank: the model uses a default sample value, labeled “Default (sample)”, so it works from day one.
B29: 2. Confront the checks. At the bottom of 1) Data Entry, the model compares what your entries imply with what you reported. Each REVIEW is a place where two of your numbers cannot both be true. Revise an entry or explain the gap.
B30: 3. Explore scenarios (2) What-If). Four scenarios: close rate, cycle time, deal size, and all three combined. The pro forma income statement is the constraint every scenario must pass through: an improvement only counts if it reaches operating income. Enter a target operating income to see what each lever would have to achieve.
B31: 4. Sign off. Until Finance has validated every entry, every result is labeled “Working model: not validated by Finance.”
B33: Color legend
B34: Yellow | C34: Enter or choose (client view only)
B35: Grey | C35: Calculated
B36: Blue | C36: Value the model uses, or a key result
B37: Green text | C37: Pulled from another worksheet
B39: What this model is not
B40: • Not a forecast. It describes what your system can and does produce under stated assumptions.
B41: • Not an evaluation of individual salespeople. Salespeople are measured as a system, without names, to find improvements in how the system works.
B42: • Not a benchmark ranking. Reference values can inform assumptions, but your baseline is built from your own reality.
B44: A few points
B45: This is a general model. For a sharper analysis, run it separately for each sales channel and product line, and separate new-customer revenue from revenue from existing customers. The model can be tailored to your business.
B46: “Increase leads” is not listed as a business scenario because we consider lead generation to be a more leveraged way to conduct sales prospecting. The number of leads, how to acquire them, and how much you can invest to acquire those leads are all handled in the tactical “drill down” spreadsheets that accompany this model.
B47: Scenarios for adding territories, filling open territories and hiring will be added later; ramp time and open territories are collected now so they are ready.

Sheet 1) Data Entry
A1: 1) Data Entry
A2: © 2000–2026 Growth Enablement. All rights reserved.
A3: =v_banner
A5: How to fill this in. Work through the four steps in order. Each step names who usually has the data, so you can forward this sheet to them.
A6: For each entry: type the number in “Your value” (yellow) and choose its Source. Validated by Finance = confirmed from your records. Your entry = your best number, not yet validated. Use our estimate = let the model calculate it from your other entries (shown in “Our estimate”).
A7: Leave an entry blank and the model uses a default sample value, labeled “Default (sample)”, so it works from day one. “Value used” is what the model actually uses.
A8: At the bottom, the checks compare what your numbers imply with what you reported. A REVIEW means two of your numbers cannot both be true: revise one, or explain the gap.
A11: # | B11: Entry | C11: What to enter and where to find it | D11: Unit | E11: Your value | F11: Source | G11: Our estimate | H11: Value used | I11: Basis | J11: Why it matters (original)
A12: Step 1. Financial results · Ask: Finance · Income statement for the 12-month period in scope.
A13: 1.1 | B13: Revenue | C13: Revenue for the period and scope (income statement). | D13: $ | G13: — | H13: =v_revenue | I13: ='1) Data Entry Logic'!J8
A14: 1.2 | B14: Contracts closed | C14: Executed agreements in the period that produced that revenue. | D14: count | G14: — | H14: =v_contracts | I14: ='1) Data Entry Logic'!J9
A15: 1.3 | B15: Cost of revenue ($), optional | C15: Direct cost of delivering that revenue. Lets us estimate the % below. | D15: $ | G15: — | H15: =v_cost_of_revenue_amt | I15: ='1) Data Entry Logic'!J10
A16: 1.4 | B16: Cost of revenue, % of revenue | C16: Cost of revenue ÷ revenue. | D16: % | G16: ='1) Data Entry Logic'!E11 | H16: =v_cost_of_revenue_pct | I16: ='1) Data Entry Logic'!J11
A17: 1.5 | B17: Research and development ($), optional | C17: R&D expense for the period. | D17: $ | G17: — | H17: =v_rnd_amt | I17: ='1) Data Entry Logic'!J12
A18: 1.6 | B18: R&D, % of revenue | C18: R&D ÷ revenue. | D18: % | G18: ='1) Data Entry Logic'!E13 | H18: =v_rnd_pct | I18: ='1) Data Entry Logic'!J13
A19: 1.7 | B19: General and administrative ($), optional | C19: G&A expense for the period. | D19: $ | G19: — | H19: =v_gna_amt | I19: ='1) Data Entry Logic'!J14
A20: 1.8 | B20: G&A, % of revenue | C20: G&A ÷ revenue. | D20: % | G20: ='1) Data Entry Logic'!E15 | H20: =v_gna_pct | I20: ='1) Data Entry Logic'!J15
A21: Step 2. Sales and marketing costs · Ask: Finance · General ledger detail for sales and marketing cost centers; payroll; expense reports.
A22: 2.1 | B22: Average base salary per salesperson | C22: Quota-carrying salespeople only; excludes managers, sales engineers and executives (payroll). | D22: $ | G22: — | H22: =v_base_salary | I22: ='1) Data Entry Logic'!J16
A23: 2.2 | B23: Benefits and payroll tax load | C23: Benefits and payroll taxes ÷ base salary. | D23: % | G23: — | H23: =v_load_rate | I23: ='1) Data Entry Logic'!J17
A24: 2.3 | B24: Fully loaded salary per salesperson | C24: Base salary plus benefits and payroll taxes. | D24: $ | G24: ='1) Data Entry Logic'!E18 | H24: =v_loaded_salary | I24: ='1) Data Entry Logic'!J18 | J24: To help develop the most effective market development effort, we must better understand our cost of sales and what drives them. Right now we are focusing on the salaries of the sales team only. Do not count salaries of non-quota carrying managers, sales engineers, or other executives. Your CFO should know what your benefits load rate is. This metric assumes a fully loaded resource (insurance, 401K, FICA, allocation of overhead, etc).
A25: 2.4 | B25: Travel per trip: air, train, mileage | C25: Round trip, one salesperson. | D25: $ | G25: — | H25: =v_trip_fare | I25: ='1) Data Entry Logic'!J19
A26: 2.5 | B26: Travel per trip: cabs, tolls, rental | C26: Per trip. | D26: $ | G26: — | H26: =v_trip_ground | I26: ='1) Data Entry Logic'!J20
A27: 2.6 | B27: Meals per day | C27: Breakfast, lunch, dinner. | D27: $ | G27: — | H27: =v_trip_meals | I27: ='1) Data Entry Logic'!J21
A28: 2.7 | B28: Lodging per night | C28: Average room cost. | D28: $ | G28: — | H28: =v_trip_lodging | I28: ='1) Data Entry Logic'!J22
A29: 2.8 | B29: Days per trip | C29: Days away per trip. | D29: count | G29: — | H29: =v_trip_days | I29: ='1) Data Entry Logic'!J23
A30: 2.9 | B30: Entertainment per trip | C30: Client meals and events per trip. | D30: $ | G30: — | H30: =v_trip_entertainment | I30: ='1) Data Entry Logic'!J24
A31: 2.10 | B31: Trips per year | C31: Sales trips per salesperson per year. | D31: count | G31: — | H31: =v_trips_per_year | I31: ='1) Data Entry Logic'!J25
A32: 2.11 | B32: Travel cost per salesperson | C32: Best: travel and entertainment ledger for quota salespeople ÷ salespeople. Otherwise use the trip build-up above. | D32: $ | G32: ='1) Data Entry Logic'!E26 | H32: =v_travel_per_salesperson | I32: ='1) Data Entry Logic'!J26 | J32: Most CFO's track overall travel expenses and try to reduce costs by limiting per diems, hotel expenses, etc. However, the real driver is a sales call. Sales people only incur these travel costs on the road. The best way to reduce travel costs is to get a better return out of each sales trip. Oftentimes, sales people will go on multiple client site visits to gain information easily gathered over the phone, or to have meetings with buyers who lack the right marketing materials to decide to buy your solution. Below are the elements of a sales trip. Estimate the costs assumed for each sales trip. Again, only assume the cost of a single sales person. Sales engineers and other costs are too complex for simple analysis.
A33: 2.12 | B33: Commissions paid ($), optional | C33: Commission expense for quota salespeople in the period. | D33: $ | G33: — | H33: =v_commissions_paid | I33: ='1) Data Entry Logic'!J27
A34: 2.13 | B34: Commission rate | C34: Commission as a share of revenue (compensation plan). | D34: % | G34: ='1) Data Entry Logic'!E28 | H34: =v_commission_rate | I34: ='1) Data Entry Logic'!J28 | J34: Commissions are the most logical and well understood driver of variable sales costs. Simply enter your sales forces average commission. Again, for simple analysis - just use an average. This model can be modified to accommodate your whole compensation plan.
A35: 2.14 | B35: Non-quota sales manager salaries | C35: Managers who carry no quota. | D35: $ | G35: — | H35: =v_oh_managers | I35: ='1) Data Entry Logic'!J29
A36: 2.15 | B36: Sales engineers and other non-quota support | C36: Pre-sales and support roles. | D36: $ | G36: — | H36: =v_oh_engineers | I36: ='1) Data Entry Logic'!J30
A37: 2.16 | B37: Sales operations and administration | C37: Sales ops and admin staff. | D37: $ | G37: — | H37: =v_oh_admin | I37: ='1) Data Entry Logic'!J31
A38: 2.17 | B38: Training | C38: Training, travel for training, related headcount. | D38: $ | G38: — | H38: =v_oh_training | I38: ='1) Data Entry Logic'!J32
A39: 2.18 | B39: Non-quota incentives | C39: Contests, recognition trips, non-quota commissions. | D39: $ | G39: — | H39: =v_oh_incentives | I39: ='1) Data Entry Logic'!J33
A40: 2.19 | B40: Sales overhead (total) | C40: Non-variable cost of running the sales organization. | D40: $ | G40: ='1) Data Entry Logic'!E34 | H40: =v_sales_overhead | I40: ='1) Data Entry Logic'!J34 | J40: Our goal with this exercise is to assess how well your company is is utilizing its sales and marketing assets. To do this, we have to examine all of the associated costs that are related to sales and marketing performance. This will help you put these investments in the right context and determine the effectiveness of these investments. This tracks all of the non-variable costs associated with running a sales organization, and includes executive salaries, sales support, training, and performance plans.
A41: 2.20 | B41: Marketing personnel | C41: All marketing staff. | D41: $ | G41: — | H41: =v_mk_people | I41: ='1) Data Entry Logic'!J35
A42: 2.21 | B42: Website | C42: Website investment and maintenance. | D42: $ | G42: — | H42: =v_mk_web | I42: ='1) Data Entry Logic'!J36
A43: 2.22 | B43: Events | C43: Online events and roadshows. | D43: $ | G43: — | H43: =v_mk_events | I43: ='1) Data Entry Logic'!J37
A44: 2.23 | B44: Advertising | C44: Paid media. | D44: $ | G44: — | H44: =v_mk_ads | I44: ='1) Data Entry Logic'!J38
A45: 2.24 | B45: Direct mail | C45: Print and online. | D45: $ | G45: — | H45: =v_mk_mail | I45: ='1) Data Entry Logic'!J39
A46: 2.25 | B46: Lead generation programs | C46: Telemarketing and other lead generation. | D46: $ | G46: — | H46: =v_mk_leadgen | I46: ='1) Data Entry Logic'!J40
A47: 2.26 | B47: Branding and public relations | C47: Identity, PR, consulting. | D47: $ | G47: — | H47: =v_mk_brand | I47: ='1) Data Entry Logic'!J41
A48: 2.27 | B48: Collateral | C48: Sales tools, white papers, brochures, printing. | D48: $ | G48: — | H48: =v_mk_collateral | I48: ='1) Data Entry Logic'!J42
A49: 2.28 | B49: Marketing (total) | C49: Investment the company makes to help drive revenue. | D49: $ | G49: ='1) Data Entry Logic'!E43 | H49: =v_marketing | I49: ='1) Data Entry Logic'!J43 | J49: This tracks all of the overall investments the company makes to help drive revenue. Marketing resources are extremely important to consider because in most organizations the sales and marketing departments are not coordinated and this results in tremendous waste.
A50: Step 3. Territories and salespeople · Ask: Sales Operations and HR · Territory plan and the roster of quota-carrying salespeople.
A51: 3.1 | B51: Funded territories | C51: Territories the company has decided to fund, filled or open. A territory is a design choice, not a person. | D51: count | G51: — | H51: =v_territory_count | I51: ='1) Data Entry Logic'!J44 | J51: Enter the number of open sales territories you had last year. This is not based on individual people, so if someone has left the company, but the territory is still open, count that as a sales territory.
A52: 3.2 | B52: Open territories at period end | C52: Funded territories with no salesperson assigned. | D52: count | G52: — | H52: =v_open_territories | I52: ='1) Data Entry Logic'!J45
A53: 3.3 | B53: Quota-carrying salespeople | C53: People in quota-carrying roles at period end (roster, no names). If blank, funded − open territories. | D53: count | G53: ='1) Data Entry Logic'!E46 | H53: =v_filled_seats | I53: ='1) Data Entry Logic'!J46
A54: 3.4 | B54: Ramp time (months) | C54: Months until a new salesperson reaches average productivity. | D54: months | G54: — | H54: =v_ramp_months | I54: ='1) Data Entry Logic'!J47 | J54: How long does it take to get a new sales person up to speed to where they are operating at maximum efficiency? Most high tech companies do a good job of training sales people on what their products are, but do very little to help them understand WHY the product is important or how to sell it. This leads to lengthy "ramp up" times. We recommend getting this figure from a sales manager.
A55: Step 4. Pipeline and sales mechanics · Ask: Sales Operations · CRM report of opportunities closed in the period, and month-end open opportunities.
A56: 4.1 | B56: Qualified opportunities won, optional | C56: Closed as won in the period (CRM). | D56: count | G56: — | H56: =v_opps_won | I56: ='1) Data Entry Logic'!J48
A57: 4.2 | B57: Qualified opportunities lost, optional | C57: Closed as lost in the period (CRM). | D57: count | G57: — | H57: =v_opps_lost | I57: ='1) Data Entry Logic'!J49
A58: 4.3 | B58: Close rate | C58: Won ÷ (won + lost) qualified opportunities, by count. | D58: % | G58: ='1) Data Entry Logic'!E50 | H58: =v_win_rate | I58: ='1) Data Entry Logic'!J50 | J58: This certainly can mean a lot of things to different people. Here we want to understand the effectiveness of how well your organization manages the sales process from first sales meeting to eventual close. Please estimate the percentage of all of the pipeline opportunities that your organization has worked that have resulted in an executed agreement.
A59: 4.4 | B59: Sales cycle (months) | C59: Median months from qualified opportunity to signature, for won deals (CRM). | D59: months | G59: — | H59: =v_cycle_months | I59: ='1) Data Entry Logic'!J51 | J59: Tracks how long from when a qualified opportunity enters the pipeline to when it closes as a sale. Your sales process may have many steps, so for simplicity track the time it takes from first meeting to the date the agreement is received by accounting. Most organizations do not track this information, so if you do not have the data - make an estimate. The single greatest impact you can have on your business is to shorten your sales cycle times.
A60: 4.5 | B60: Average revenue per contract | C60: Average deal size. Our estimate is revenue ÷ contracts. | D60: $ | G60: ='1) Data Entry Logic'!E52 | H60: =v_deal_size | I60: ='1) Data Entry Logic'!J52 | J60: This is the average deal size for your company. For this simple analysis, you can get this figure by dividing your revenue by total number of contracts. For more detailed analysis, we recommend that you break things down into product lines, services offerings, and sales channels. You should also separate new client revenue from upselling your installed base. For professional services, credit the total esimated hours for a project towards one sales transaction.
A61: 4.6 | B61: Open qualified opportunities, optional | C61: Average of month-end open qualified opportunities across all salespeople (CRM). | D61: count | G61: — | H61: =v_open_opps_total | I61: ='1) Data Entry Logic'!J53
A62: 4.7 | B62: Opportunities a salesperson can manage at once | C62: Most qualified opportunities a salesperson can hold and advance well at the same time. | D62: count | G62: — | H62: =v_opportunities_capacity | I62: ='1) Data Entry Logic'!J54 | J62: One driver of sales force inefficiency is the amount of NON-selling time spent by sales people. Some companies estimate as much at 50% of their time is invested in "non-selling" activities. Our studies reveal that a larger portion of that time in spend in activitity that isn't value-added to customers. The best way to financially measure that impact is by monitoring the number of accounts any given sales person can effectively manage at the same time. The greater amount of time you allow your sales people to sell - the more opportunities they can work in a given year.
A65: Checks: do your numbers agree with each other?
B66: Check | C66: What it compares | E66: Model implies | F66: You reported | G66: Gap | H66: Status | I66: Entries involved | J66: What to do
A67: 1 | B67: Deal size | C67: Revenue ÷ contracts, compared with the deal size used | E67: ='1) Data Entry Logic'!D60 | F67: ='1) Data Entry Logic'!E60 | G67: ='1) Data Entry Logic'!F60 | H67: ='1) Data Entry Logic'!H60 | I67: Revenue, contracts, deal size | J67: =IF(H67="REVIEW","These entries cannot all be true. Revise one, or write the explanation here.",IF(H67="NEEDS DATA","Enter the optional data above to run this check.",""))
A68: 2 | B68: Revenue | C68: Revenue the model produces at baseline, compared with revenue reported | E68: ='1) Data Entry Logic'!D61 | F68: ='1) Data Entry Logic'!E61 | G68: ='1) Data Entry Logic'!F61 | H68: ='1) Data Entry Logic'!H61 | I68: Salespeople, capacity, opportunities held, cycle, close rate, deal size, revenue | J68: =IF(H68="REVIEW","These entries cannot all be true. Revise one, or write the explanation here.",IF(H68="NEEDS DATA","Enter the optional data above to run this check.",""))
A69: 3 | B69: Contracts | C69: Contracts the model produces at baseline, compared with contracts reported | E69: ='1) Data Entry Logic'!D62 | F69: ='1) Data Entry Logic'!E62 | G69: ='1) Data Entry Logic'!F62 | H69: ='1) Data Entry Logic'!H62 | I69: Salespeople, capacity, opportunities held, cycle, close rate, contracts | J69: =IF(H69="REVIEW","These entries cannot all be true. Revise one, or write the explanation here.",IF(H69="NEEDS DATA","Enter the optional data above to run this check.",""))
A70: 4 | B70: Close rate | C70: CRM won ÷ (won + lost), compared with the close rate used | E70: ='1) Data Entry Logic'!D63 | F70: ='1) Data Entry Logic'!E63 | G70: ='1) Data Entry Logic'!F63 | H70: ='1) Data Entry Logic'!H63 | I70: Opportunities won and lost, close rate | J70: =IF(H70="REVIEW","These entries cannot all be true. Revise one, or write the explanation here.",IF(H70="NEEDS DATA","Enter the optional data above to run this check.",""))
A71: 5 | B71: Commission | C71: Commissions paid ÷ revenue, compared with the commission rate used | E71: ='1) Data Entry Logic'!D64 | F71: ='1) Data Entry Logic'!E64 | G71: ='1) Data Entry Logic'!F64 | H71: ='1) Data Entry Logic'!H64 | I71: Commissions paid, revenue, commission rate | J71: =IF(H71="REVIEW","These entries cannot all be true. Revise one, or write the explanation here.",IF(H71="NEEDS DATA","Enter the optional data above to run this check.",""))
A72: 6 | B72: Little's Law | C72: Opportunities each salesperson must hold to close the reported contracts (contracts ÷ close rate ÷ salespeople × cycle ÷ 12), compared with opportunities held in the CRM | E72: ='1) Data Entry Logic'!D65 | F72: ='1) Data Entry Logic'!E65 | G72: ='1) Data Entry Logic'!F65 | H72: ='1) Data Entry Logic'!H65 | I72: Contracts, close rate, salespeople, cycle, open opportunities | J72: =IF(H72="REVIEW","These entries cannot all be true. Revise one, or write the explanation here.",IF(H72="NEEDS DATA","Enter the optional data above to run this check.",""))
A73: 7 | B73: Territories | C73: Salespeople + open territories, compared with funded territories (runs only when the salesperson count is entered, not estimated) | E73: ='1) Data Entry Logic'!D66 | F73: ='1) Data Entry Logic'!E66 | G73: ='1) Data Entry Logic'!F66 | H73: ='1) Data Entry Logic'!H66 | I73: Salespeople, open territories, funded territories | J73: =IF(H73="REVIEW","These entries cannot all be true. Revise one, or write the explanation here.",IF(H73="NEEDS DATA","Enter the optional data above to run this check.",""))
B75: Source of the values used
B76: Validated by Finance | C76: =COUNTIF('1) Data Entry Logic'!$J$8:$J$54,"Validated by Finance*")
B77: Your entry (not validated) | C77: =COUNTIF('1) Data Entry Logic'!$J$8:$J$54,"Your entry (not validated)*")
B78: Our estimate | C78: =COUNTIF('1) Data Entry Logic'!$J$8:$J$54,"Our estimate*")
B79: Default (sample) | C79: =COUNTIF('1) Data Entry Logic'!$J$8:$J$54,"Default (sample)*")
B80: Not provided (optional) | C80: =COUNTIF('1) Data Entry Logic'!$J$8:$J$54,"Not provided (optional)*")

Sheet 1) Data Entry Logic
A1: 1) Data Entry Logic
A2: Programming logic for the data entry. Nothing here is typed by the client; every cell is a formula or a fixed default.
A3: Rule for Value used: if Source = “Use our estimate” and an estimate exists → Our estimate; otherwise, if Your value is entered → Your value; otherwise → Default.
A4: Rule for Basis: Validated by Finance (value entered and source = Validated by Finance) · Your entry (not validated) · Our estimate · Default (sample) · Not provided (optional entry left blank).
A5: Every Value used cell is a workbook name, v_<ID>. It is the only way any other worksheet reads an entry.
A7: ID | B7: Entry | C7: Your value | D7: Source chosen | E7: Our estimate | F7: How our estimate is calculated | G7: Default | H7: Default context | I7: Value used | J7: Basis | K7: What would prove it wrong | L7: Used by
A8: revenue | B8: Revenue | C8: =IF('1) Data Entry'!E13="","",'1) Data Entry'!E13) | D8: =IF('1) Data Entry'!F13="","",'1) Data Entry'!F13) | F8: No estimate: enter a value or use the default | G8: 25000000 | H8: As-is model sample (illustrative) | I8: =IF(AND(D8="Use our estimate",E8<>""),E8,IF(C8<>"",C8,G8)) | J8: =IF(I8="","Not provided (optional)",IF(AND(D8="Use our estimate",E8<>""),"Our estimate",IF(C8<>"",IF(D8="Validated by Finance","Validated by Finance","Your entry (not validated)"),"Default (sample)"))) | K8: Model baseline revenue differs from it (revenue check) | L8: Checks: revenue, deal size, commission
A9: contracts | B9: Contracts closed | C9: =IF('1) Data Entry'!E14="","",'1) Data Entry'!E14) | D9: =IF('1) Data Entry'!F14="","",'1) Data Entry'!F14) | F9: No estimate: enter a value or use the default | G9: 755 | H9: As-is model sample (illustrative) | I9: =IF(AND(D9="Use our estimate",E9<>""),E9,IF(C9<>"",C9,G9)) | J9: =IF(I9="","Not provided (optional)",IF(AND(D9="Use our estimate",E9<>""),"Our estimate",IF(C9<>"",IF(D9="Validated by Finance","Validated by Finance","Your entry (not validated)"),"Default (sample)"))) | K9: Won opportunities in the CRM differ; model contracts differ (contracts check) | L9: Checks: contracts, deal size
A10: cost_of_revenue_amt | B10: Cost of revenue ($), optional | C10: =IF('1) Data Entry'!E15="","",'1) Data Entry'!E15) | D10: =IF('1) Data Entry'!F15="","",'1) Data Entry'!F15) | F10: No estimate: enter a value or use the default | G10: ="" | H10: Optional; no default | I10: =IF(AND(D10="Use our estimate",E10<>""),E10,IF(C10<>"",C10,G10)) | J10: =IF(I10="","Not provided (optional)",IF(AND(D10="Use our estimate",E10<>""),"Our estimate",IF(C10<>"",IF(D10="Validated by Finance","Validated by Finance","Your entry (not validated)"),"Default (sample)"))) | L10: Estimate of cost of revenue %
A11: cost_of_revenue_pct | B11: Cost of revenue, % of revenue | C11: =IF('1) Data Entry'!E16="","",'1) Data Entry'!E16) | D11: =IF('1) Data Entry'!F16="","",'1) Data Entry'!F16) | E11: =IFERROR(IF(OR(v_cost_of_revenue_amt="",v_revenue=""),"",v_cost_of_revenue_amt/v_revenue),"") | F11: Cost of revenue ($) ÷ revenue | G11: 0.1322 | H11: As-is model sample (illustrative) | I11: =IF(AND(D11="Use our estimate",E11<>""),E11,IF(C11<>"",C11,G11)) | J11: =IF(I11="","Not provided (optional)",IF(AND(D11="Use our estimate",E11<>""),"Our estimate",IF(C11<>"",IF(D11="Validated by Finance","Validated by Finance","Your entry (not validated)"),"Default (sample)"))) | K11: Income statement history shows a different ratio or a fixed part | L11: Income statement: cost of revenue
A12: rnd_amt | B12: Research and development ($), optional | C12: =IF('1) Data Entry'!E17="","",'1) Data Entry'!E17) | D12: =IF('1) Data Entry'!F17="","",'1) Data Entry'!F17) | F12: No estimate: enter a value or use the default | G12: ="" | H12: Optional; no default | I12: =IF(AND(D12="Use our estimate",E12<>""),E12,IF(C12<>"",C12,G12)) | J12: =IF(I12="","Not provided (optional)",IF(AND(D12="Use our estimate",E12<>""),"Our estimate",IF(C12<>"",IF(D12="Validated by Finance","Validated by Finance","Your entry (not validated)"),"Default (sample)"))) | L12: Estimate of R&D %
A13: rnd_pct | B13: R&D, % of revenue | C13: =IF('1) Data Entry'!E18="","",'1) Data Entry'!E18) | D13: =IF('1) Data Entry'!F18="","",'1) Data Entry'!F18) | E13: =IFERROR(IF(OR(v_revenue="",v_rnd_amt=""),"",v_rnd_amt/v_revenue),"") | F13: R&D ($) ÷ revenue | G13: 0.1019 | H13: As-is model sample (illustrative) | I13: =IF(AND(D13="Use our estimate",E13<>""),E13,IF(C13<>"",C13,G13)) | J13: =IF(I13="","Not provided (optional)",IF(AND(D13="Use our estimate",E13<>""),"Our estimate",IF(C13<>"",IF(D13="Validated by Finance","Validated by Finance","Your entry (not validated)"),"Default (sample)"))) | K13: R&D does not move with revenue | L13: Income statement: R&D
A14: gna_amt | B14: General and administrative ($), optional | C14: =IF('1) Data Entry'!E19="","",'1) Data Entry'!E19) | D14: =IF('1) Data Entry'!F19="","",'1) Data Entry'!F19) | F14: No estimate: enter a value or use the default | G14: ="" | H14: Optional; no default | I14: =IF(AND(D14="Use our estimate",E14<>""),E14,IF(C14<>"",C14,G14)) | J14: =IF(I14="","Not provided (optional)",IF(AND(D14="Use our estimate",E14<>""),"Our estimate",IF(C14<>"",IF(D14="Validated by Finance","Validated by Finance","Your entry (not validated)"),"Default (sample)"))) | L14: Estimate of G&A %
A15: gna_pct | B15: G&A, % of revenue | C15: =IF('1) Data Entry'!E20="","",'1) Data Entry'!E20) | D15: =IF('1) Data Entry'!F20="","",'1) Data Entry'!F20) | E15: =IFERROR(IF(OR(v_gna_amt="",v_revenue=""),"",v_gna_amt/v_revenue),"") | F15: G&A ($) ÷ revenue | G15: 0.154 | H15: As-is model sample (illustrative) | I15: =IF(AND(D15="Use our estimate",E15<>""),E15,IF(C15<>"",C15,G15)) | J15: =IF(I15="","Not provided (optional)",IF(AND(D15="Use our estimate",E15<>""),"Our estimate",IF(C15<>"",IF(D15="Validated by Finance","Validated by Finance","Your entry (not validated)"),"Default (sample)"))) | K15: G&A does not move with revenue | L15: Income statement: G&A
A16: base_salary | B16: Average base salary per salesperson | C16: =IF('1) Data Entry'!E22="","",'1) Data Entry'!E22) | D16: =IF('1) Data Entry'!F22="","",'1) Data Entry'!F22) | F16: No estimate: enter a value or use the default | G16: 95000 | H16: As-is model sample (illustrative) | I16: =IF(AND(D16="Use our estimate",E16<>""),E16,IF(C16<>"",C16,G16)) | J16: =IF(I16="","Not provided (optional)",IF(AND(D16="Use our estimate",E16<>""),"Our estimate",IF(C16<>"",IF(D16="Validated by Finance","Validated by Finance","Your entry (not validated)"),"Default (sample)"))) | L16: Estimate of fully loaded salary
A17: load_rate | B17: Benefits and payroll tax load | C17: =IF('1) Data Entry'!E23="","",'1) Data Entry'!E23) | D17: =IF('1) Data Entry'!F23="","",'1) Data Entry'!F23) | F17: No estimate: enter a value or use the default | G17: 0.23 | H17: As-is model sample (illustrative) | I17: =IF(AND(D17="Use our estimate",E17<>""),E17,IF(C17<>"",C17,G17)) | J17: =IF(I17="","Not provided (optional)",IF(AND(D17="Use our estimate",E17<>""),"Our estimate",IF(C17<>"",IF(D17="Validated by Finance","Validated by Finance","Your entry (not validated)"),"Default (sample)"))) | L17: Estimate of fully loaded salary
A18: loaded_salary | B18: Fully loaded salary per salesperson | C18: =IF('1) Data Entry'!E24="","",'1) Data Entry'!E24) | D18: =IF('1) Data Entry'!F24="","",'1) Data Entry'!F24) | E18: =IFERROR(IF(OR(v_base_salary="",v_load_rate=""),"",v_base_salary*(1+v_load_rate)),"") | F18: Base salary × (1 + load) | G18: =E18 | H18: Our estimate | I18: =IF(AND(D18="Use our estimate",E18<>""),E18,IF(C18<>"",C18,G18)) | J18: =IF(I18="","Not provided (optional)",IF(AND(D18="Use our estimate",E18<>""),"Our estimate",IF(C18<>"",IF(D18="Validated by Finance","Validated by Finance","Your entry (not validated)"),"Our estimate"))) | K18: Payroll for quota-carrying salespeople ÷ salespeople differs | L18: Income statement: salesperson pay
A19: trip_fare | B19: Travel per trip: air, train, mileage | C19: =IF('1) Data Entry'!E25="","",'1) Data Entry'!E25) | D19: =IF('1) Data Entry'!F25="","",'1) Data Entry'!F25) | F19: No estimate: enter a value or use the default | G19: 750 | H19: As-is model sample (illustrative) | I19: =IF(AND(D19="Use our estimate",E19<>""),E19,IF(C19<>"",C19,G19)) | J19: =IF(I19="","Not provided (optional)",IF(AND(D19="Use our estimate",E19<>""),"Our estimate",IF(C19<>"",IF(D19="Validated by Finance","Validated by Finance","Your entry (not validated)"),"Default (sample)"))) | L19: Estimate of travel per salesperson
A20: trip_ground | B20: Travel per trip: cabs, tolls, rental | C20: =IF('1) Data Entry'!E26="","",'1) Data Entry'!E26) | D20: =IF('1) Data Entry'!F26="","",'1) Data Entry'!F26) | F20: No estimate: enter a value or use the default | G20: 200 | H20: As-is model sample (illustrative) | I20: =IF(AND(D20="Use our estimate",E20<>""),E20,IF(C20<>"",C20,G20)) | J20: =IF(I20="","Not provided (optional)",IF(AND(D20="Use our estimate",E20<>""),"Our estimate",IF(C20<>"",IF(D20="Validated by Finance","Validated by Finance","Your entry (not validated)"),"Default (sample)"))) | L20: Estimate of travel per salesperson
A21: trip_meals | B21: Meals per day | C21: =IF('1) Data Entry'!E27="","",'1) Data Entry'!E27) | D21: =IF('1) Data Entry'!F27="","",'1) Data Entry'!F27) | F21: No estimate: enter a value or use the default | G21: 100 | H21: As-is model sample (illustrative) | I21: =IF(AND(D21="Use our estimate",E21<>""),E21,IF(C21<>"",C21,G21)) | J21: =IF(I21="","Not provided (optional)",IF(AND(D21="Use our estimate",E21<>""),"Our estimate",IF(C21<>"",IF(D21="Validated by Finance","Validated by Finance","Your entry (not validated)"),"Default (sample)"))) | L21: Estimate of travel per salesperson
A22: trip_lodging | B22: Lodging per night | C22: =IF('1) Data Entry'!E28="","",'1) Data Entry'!E28) | D22: =IF('1) Data Entry'!F28="","",'1) Data Entry'!F28) | F22: No estimate: enter a value or use the default | G22: 250 | H22: As-is model sample (illustrative) | I22: =IF(AND(D22="Use our estimate",E22<>""),E22,IF(C22<>"",C22,G22)) | J22: =IF(I22="","Not provided (optional)",IF(AND(D22="Use our estimate",E22<>""),"Our estimate",IF(C22<>"",IF(D22="Validated by Finance","Validated by Finance","Your entry (not validated)"),"Default (sample)"))) | L22: Estimate of travel per salesperson
A23: trip_days | B23: Days per trip | C23: =IF('1) Data Entry'!E29="","",'1) Data Entry'!E29) | D23: =IF('1) Data Entry'!F29="","",'1) Data Entry'!F29) | F23: No estimate: enter a value or use the default | G23: 2 | H23: As-is model sample (illustrative) | I23: =IF(AND(D23="Use our estimate",E23<>""),E23,IF(C23<>"",C23,G23)) | J23: =IF(I23="","Not provided (optional)",IF(AND(D23="Use our estimate",E23<>""),"Our estimate",IF(C23<>"",IF(D23="Validated by Finance","Validated by Finance","Your entry (not validated)"),"Default (sample)"))) | L23: Estimate of travel per salesperson
A24: trip_entertainment | B24: Entertainment per trip | C24: =IF('1) Data Entry'!E30="","",'1) Data Entry'!E30) | D24: =IF('1) Data Entry'!F30="","",'1) Data Entry'!F30) | F24: No estimate: enter a value or use the default | G24: 250 | H24: As-is model sample (illustrative) | I24: =IF(AND(D24="Use our estimate",E24<>""),E24,IF(C24<>"",C24,G24)) | J24: =IF(I24="","Not provided (optional)",IF(AND(D24="Use our estimate",E24<>""),"Our estimate",IF(C24<>"",IF(D24="Validated by Finance","Validated by Finance","Your entry (not validated)"),"Default (sample)"))) | L24: Estimate of travel per salesperson
A25: trips_per_year | B25: Trips per year | C25: =IF('1) Data Entry'!E31="","",'1) Data Entry'!E31) | D25: =IF('1) Data Entry'!F31="","",'1) Data Entry'!F31) | F25: No estimate: enter a value or use the default | G25: 25 | H25: As-is model sample (illustrative) | I25: =IF(AND(D25="Use our estimate",E25<>""),E25,IF(C25<>"",C25,G25)) | J25: =IF(I25="","Not provided (optional)",IF(AND(D25="Use our estimate",E25<>""),"Our estimate",IF(C25<>"",IF(D25="Validated by Finance","Validated by Finance","Your entry (not validated)"),"Default (sample)"))) | L25: Estimate of travel per salesperson
A26: travel_per_salesperson | B26: Travel cost per salesperson | C26: =IF('1) Data Entry'!E32="","",'1) Data Entry'!E32) | D26: =IF('1) Data Entry'!F32="","",'1) Data Entry'!F32) | E26: =IFERROR(IF(OR(v_trip_days="",v_trip_entertainment="",v_trip_fare="",v_trip_ground="",v_trip_lodging="",v_trip_meals="",v_trips_per_year=""),"",((v_trip_fare+v_trip_ground+v_trip_entertainment)+v_trip_days*(v_trip_meals+v_trip_lodging))*v_trips_per_year),"") | F26: (fare + ground + entertainment + days × (meals + lodging)) × trips per year | G26: =E26 | H26: Our estimate | I26: =IF(AND(D26="Use our estimate",E26<>""),E26,IF(C26<>"",C26,G26)) | J26: =IF(I26="","Not provided (optional)",IF(AND(D26="Use our estimate",E26<>""),"Our estimate",IF(C26<>"",IF(D26="Validated by Finance","Validated by Finance","Your entry (not validated)"),"Our estimate"))) | K26: Travel ledger for quota salespeople differs | L26: Income statement: salesperson travel
A27: commissions_paid | B27: Commissions paid ($), optional | C27: =IF('1) Data Entry'!E33="","",'1) Data Entry'!E33) | D27: =IF('1) Data Entry'!F33="","",'1) Data Entry'!F33) | F27: No estimate: enter a value or use the default | G27: ="" | H27: Optional; no default | I27: =IF(AND(D27="Use our estimate",E27<>""),E27,IF(C27<>"",C27,G27)) | J27: =IF(I27="","Not provided (optional)",IF(AND(D27="Use our estimate",E27<>""),"Our estimate",IF(C27<>"",IF(D27="Validated by Finance","Validated by Finance","Your entry (not validated)"),"Default (sample)"))) | L27: Estimate and check of commission rate
A28: commission_rate | B28: Commission rate | C28: =IF('1) Data Entry'!E34="","",'1) Data Entry'!E34) | D28: =IF('1) Data Entry'!F34="","",'1) Data Entry'!F34) | E28: =IFERROR(IF(OR(v_commissions_paid="",v_revenue=""),"",v_commissions_paid/v_revenue),"") | F28: Commissions paid ÷ revenue | G28: 0.08 | H28: As-is model sample (illustrative) | I28: =IF(AND(D28="Use our estimate",E28<>""),E28,IF(C28<>"",C28,G28)) | J28: =IF(I28="","Not provided (optional)",IF(AND(D28="Use our estimate",E28<>""),"Our estimate",IF(C28<>"",IF(D28="Validated by Finance","Validated by Finance","Your entry (not validated)"),"Default (sample)"))) | K28: Commissions paid ÷ revenue differs from the plan rate (commission check) | L28: Income statement: commissions
A29: oh_managers | B29: Non-quota sales manager salaries | C29: =IF('1) Data Entry'!E35="","",'1) Data Entry'!E35) | D29: =IF('1) Data Entry'!F35="","",'1) Data Entry'!F35) | F29: No estimate: enter a value or use the default | G29: 2750000 | H29: As-is model sample (illustrative) | I29: =IF(AND(D29="Use our estimate",E29<>""),E29,IF(C29<>"",C29,G29)) | J29: =IF(I29="","Not provided (optional)",IF(AND(D29="Use our estimate",E29<>""),"Our estimate",IF(C29<>"",IF(D29="Validated by Finance","Validated by Finance","Your entry (not validated)"),"Default (sample)"))) | L29: Estimate of sales overhead
A30: oh_engineers | B30: Sales engineers and other non-quota support | C30: =IF('1) Data Entry'!E36="","",'1) Data Entry'!E36) | D30: =IF('1) Data Entry'!F36="","",'1) Data Entry'!F36) | F30: No estimate: enter a value or use the default | G30: 6000000 | H30: As-is model sample (illustrative) | I30: =IF(AND(D30="Use our estimate",E30<>""),E30,IF(C30<>"",C30,G30)) | J30: =IF(I30="","Not provided (optional)",IF(AND(D30="Use our estimate",E30<>""),"Our estimate",IF(C30<>"",IF(D30="Validated by Finance","Validated by Finance","Your entry (not validated)"),"Default (sample)"))) | L30: Estimate of sales overhead
A31: oh_admin | B31: Sales operations and administration | C31: =IF('1) Data Entry'!E37="","",'1) Data Entry'!E37) | D31: =IF('1) Data Entry'!F37="","",'1) Data Entry'!F37) | F31: No estimate: enter a value or use the default | G31: 800000 | H31: As-is model sample (illustrative) | I31: =IF(AND(D31="Use our estimate",E31<>""),E31,IF(C31<>"",C31,G31)) | J31: =IF(I31="","Not provided (optional)",IF(AND(D31="Use our estimate",E31<>""),"Our estimate",IF(C31<>"",IF(D31="Validated by Finance","Validated by Finance","Your entry (not validated)"),"Default (sample)"))) | L31: Estimate of sales overhead
A32: oh_training | B32: Training | C32: =IF('1) Data Entry'!E38="","",'1) Data Entry'!E38) | D32: =IF('1) Data Entry'!F38="","",'1) Data Entry'!F38) | F32: No estimate: enter a value or use the default | G32: 500000 | H32: As-is model sample (illustrative) | I32: =IF(AND(D32="Use our estimate",E32<>""),E32,IF(C32<>"",C32,G32)) | J32: =IF(I32="","Not provided (optional)",IF(AND(D32="Use our estimate",E32<>""),"Our estimate",IF(C32<>"",IF(D32="Validated by Finance","Validated by Finance","Your entry (not validated)"),"Default (sample)"))) | L32: Estimate of sales overhead
A33: oh_incentives | B33: Non-quota incentives | C33: =IF('1) Data Entry'!E39="","",'1) Data Entry'!E39) | D33: =IF('1) Data Entry'!F39="","",'1) Data Entry'!F39) | F33: No estimate: enter a value or use the default | G33: 750000 | H33: As-is model sample (illustrative) | I33: =IF(AND(D33="Use our estimate",E33<>""),E33,IF(C33<>"",C33,G33)) | J33: =IF(I33="","Not provided (optional)",IF(AND(D33="Use our estimate",E33<>""),"Our estimate",IF(C33<>"",IF(D33="Validated by Finance","Validated by Finance","Your entry (not validated)"),"Default (sample)"))) | L33: Estimate of sales overhead
A34: sales_overhead | B34: Sales overhead (total) | C34: =IF('1) Data Entry'!E40="","",'1) Data Entry'!E40) | D34: =IF('1) Data Entry'!F40="","",'1) Data Entry'!F40) | E34: =IFERROR(IF(OR(v_oh_admin="",v_oh_engineers="",v_oh_incentives="",v_oh_managers="",v_oh_training=""),"",v_oh_managers+v_oh_engineers+v_oh_admin+v_oh_training+v_oh_incentives),"") | F34: Sum of the five lines above | G34: =E34 | H34: Our estimate | I34: =IF(AND(D34="Use our estimate",E34<>""),E34,IF(C34<>"",C34,G34)) | J34: =IF(I34="","Not provided (optional)",IF(AND(D34="Use our estimate",E34<>""),"Our estimate",IF(C34<>"",IF(D34="Validated by Finance","Validated by Finance","Your entry (not validated)"),"Our estimate"))) | K34: Ledger total for sales overhead differs | L34: Income statement: sales overhead
A35: mk_people | B35: Marketing personnel | C35: =IF('1) Data Entry'!E41="","",'1) Data Entry'!E41) | D35: =IF('1) Data Entry'!F41="","",'1) Data Entry'!F41) | F35: No estimate: enter a value or use the default | G35: 1000000 | H35: As-is model sample (illustrative) | I35: =IF(AND(D35="Use our estimate",E35<>""),E35,IF(C35<>"",C35,G35)) | J35: =IF(I35="","Not provided (optional)",IF(AND(D35="Use our estimate",E35<>""),"Our estimate",IF(C35<>"",IF(D35="Validated by Finance","Validated by Finance","Your entry (not validated)"),"Default (sample)"))) | L35: Estimate of marketing
A36: mk_web | B36: Website | C36: =IF('1) Data Entry'!E42="","",'1) Data Entry'!E42) | D36: =IF('1) Data Entry'!F42="","",'1) Data Entry'!F42) | F36: No estimate: enter a value or use the default | G36: 250000 | H36: As-is model sample (illustrative) | I36: =IF(AND(D36="Use our estimate",E36<>""),E36,IF(C36<>"",C36,G36)) | J36: =IF(I36="","Not provided (optional)",IF(AND(D36="Use our estimate",E36<>""),"Our estimate",IF(C36<>"",IF(D36="Validated by Finance","Validated by Finance","Your entry (not validated)"),"Default (sample)"))) | L36: Estimate of marketing
A37: mk_events | B37: Events | C37: =IF('1) Data Entry'!E43="","",'1) Data Entry'!E43) | D37: =IF('1) Data Entry'!F43="","",'1) Data Entry'!F43) | F37: No estimate: enter a value or use the default | G37: 500000 | H37: As-is model sample (illustrative) | I37: =IF(AND(D37="Use our estimate",E37<>""),E37,IF(C37<>"",C37,G37)) | J37: =IF(I37="","Not provided (optional)",IF(AND(D37="Use our estimate",E37<>""),"Our estimate",IF(C37<>"",IF(D37="Validated by Finance","Validated by Finance","Your entry (not validated)"),"Default (sample)"))) | L37: Estimate of marketing
A38: mk_ads | B38: Advertising | C38: =IF('1) Data Entry'!E44="","",'1) Data Entry'!E44) | D38: =IF('1) Data Entry'!F44="","",'1) Data Entry'!F44) | F38: No estimate: enter a value or use the default | G38: 500000 | H38: As-is model sample (illustrative) | I38: =IF(AND(D38="Use our estimate",E38<>""),E38,IF(C38<>"",C38,G38)) | J38: =IF(I38="","Not provided (optional)",IF(AND(D38="Use our estimate",E38<>""),"Our estimate",IF(C38<>"",IF(D38="Validated by Finance","Validated by Finance","Your entry (not validated)"),"Default (sample)"))) | L38: Estimate of marketing
A39: mk_mail | B39: Direct mail | C39: =IF('1) Data Entry'!E45="","",'1) Data Entry'!E45) | D39: =IF('1) Data Entry'!F45="","",'1) Data Entry'!F45) | F39: No estimate: enter a value or use the default | G39: 250000 | H39: As-is model sample (illustrative) | I39: =IF(AND(D39="Use our estimate",E39<>""),E39,IF(C39<>"",C39,G39)) | J39: =IF(I39="","Not provided (optional)",IF(AND(D39="Use our estimate",E39<>""),"Our estimate",IF(C39<>"",IF(D39="Validated by Finance","Validated by Finance","Your entry (not validated)"),"Default (sample)"))) | L39: Estimate of marketing
A40: mk_leadgen | B40: Lead generation programs | C40: =IF('1) Data Entry'!E46="","",'1) Data Entry'!E46) | D40: =IF('1) Data Entry'!F46="","",'1) Data Entry'!F46) | F40: No estimate: enter a value or use the default | G40: 250000 | H40: As-is model sample (illustrative) | I40: =IF(AND(D40="Use our estimate",E40<>""),E40,IF(C40<>"",C40,G40)) | J40: =IF(I40="","Not provided (optional)",IF(AND(D40="Use our estimate",E40<>""),"Our estimate",IF(C40<>"",IF(D40="Validated by Finance","Validated by Finance","Your entry (not validated)"),"Default (sample)"))) | L40: Estimate of marketing
A41: mk_brand | B41: Branding and public relations | C41: =IF('1) Data Entry'!E47="","",'1) Data Entry'!E47) | D41: =IF('1) Data Entry'!F47="","",'1) Data Entry'!F47) | F41: No estimate: enter a value or use the default | G41: 200000 | H41: As-is model sample (illustrative) | I41: =IF(AND(D41="Use our estimate",E41<>""),E41,IF(C41<>"",C41,G41)) | J41: =IF(I41="","Not provided (optional)",IF(AND(D41="Use our estimate",E41<>""),"Our estimate",IF(C41<>"",IF(D41="Validated by Finance","Validated by Finance","Your entry (not validated)"),"Default (sample)"))) | L41: Estimate of marketing
A42: mk_collateral | B42: Collateral | C42: =IF('1) Data Entry'!E48="","",'1) Data Entry'!E48) | D42: =IF('1) Data Entry'!F48="","",'1) Data Entry'!F48) | F42: No estimate: enter a value or use the default | G42: 750000 | H42: As-is model sample (illustrative) | I42: =IF(AND(D42="Use our estimate",E42<>""),E42,IF(C42<>"",C42,G42)) | J42: =IF(I42="","Not provided (optional)",IF(AND(D42="Use our estimate",E42<>""),"Our estimate",IF(C42<>"",IF(D42="Validated by Finance","Validated by Finance","Your entry (not validated)"),"Default (sample)"))) | L42: Estimate of marketing
A43: marketing | B43: Marketing (total) | C43: =IF('1) Data Entry'!E49="","",'1) Data Entry'!E49) | D43: =IF('1) Data Entry'!F49="","",'1) Data Entry'!F49) | E43: =IFERROR(IF(OR(v_mk_ads="",v_mk_brand="",v_mk_collateral="",v_mk_events="",v_mk_leadgen="",v_mk_mail="",v_mk_people="",v_mk_web=""),"",v_mk_people+v_mk_web+v_mk_events+v_mk_ads+v_mk_mail+v_mk_leadgen+v_mk_brand+v_mk_collateral),"") | F43: Sum of the eight lines above | G43: =E43 | H43: Our estimate | I43: =IF(AND(D43="Use our estimate",E43<>""),E43,IF(C43<>"",C43,G43)) | J43: =IF(I43="","Not provided (optional)",IF(AND(D43="Use our estimate",E43<>""),"Our estimate",IF(C43<>"",IF(D43="Validated by Finance","Validated by Finance","Your entry (not validated)"),"Our estimate"))) | K43: Ledger total for marketing differs | L43: Income statement: marketing
A44: territory_count | B44: Funded territories | C44: =IF('1) Data Entry'!E51="","",'1) Data Entry'!E51) | D44: =IF('1) Data Entry'!F51="","",'1) Data Entry'!F51) | F44: No estimate: enter a value or use the default | G44: 100 | H44: As-is model sample (illustrative) | I44: =IF(AND(D44="Use our estimate",E44<>""),E44,IF(C44<>"",C44,G44)) | J44: =IF(I44="","Not provided (optional)",IF(AND(D44="Use our estimate",E44<>""),"Our estimate",IF(C44<>"",IF(D44="Validated by Finance","Validated by Finance","Your entry (not validated)"),"Default (sample)"))) | K44: Filled + open territories differ from this count (territory check) | L44: Estimate of salespeople; territory check
A45: open_territories | B45: Open territories at period end | C45: =IF('1) Data Entry'!E52="","",'1) Data Entry'!E52) | D45: =IF('1) Data Entry'!F52="","",'1) Data Entry'!F52) | F45: No estimate: enter a value or use the default | G45: 0 | H45: As-is model sample (illustrative) | I45: =IF(AND(D45="Use our estimate",E45<>""),E45,IF(C45<>"",C45,G45)) | J45: =IF(I45="","Not provided (optional)",IF(AND(D45="Use our estimate",E45<>""),"Our estimate",IF(C45<>"",IF(D45="Validated by Finance","Validated by Finance","Your entry (not validated)"),"Default (sample)"))) | K45: Roster and territory plan disagree | L45: Estimate of salespeople; territory check
A46: filled_seats | B46: Quota-carrying salespeople | C46: =IF('1) Data Entry'!E53="","",'1) Data Entry'!E53) | D46: =IF('1) Data Entry'!F53="","",'1) Data Entry'!F53) | E46: =IFERROR(IF(OR(v_open_territories="",v_territory_count=""),"",v_territory_count-v_open_territories),"") | F46: Funded territories − open territories | G46: =E46 | H46: Our estimate | I46: =IF(AND(D46="Use our estimate",E46<>""),E46,IF(C46<>"",C46,G46)) | J46: =IF(I46="","Not provided (optional)",IF(AND(D46="Use our estimate",E46<>""),"Our estimate",IF(C46<>"",IF(D46="Validated by Finance","Validated by Finance","Your entry (not validated)"),"Our estimate"))) | K46: Roster count differs from filled territories | L46: Every scenario: number of salespeople
A47: ramp_months | B47: Ramp time (months) | C47: =IF('1) Data Entry'!E54="","",'1) Data Entry'!E54) | D47: =IF('1) Data Entry'!F54="","",'1) Data Entry'!F54) | F47: No estimate: enter a value or use the default | G47: 12 | H47: As-is model sample (illustrative) | I47: =IF(AND(D47="Use our estimate",E47<>""),E47,IF(C47<>"",C47,G47)) | J47: =IF(I47="","Not provided (optional)",IF(AND(D47="Use our estimate",E47<>""),"Our estimate",IF(C47<>"",IF(D47="Validated by Finance","Validated by Finance","Your entry (not validated)"),"Default (sample)"))) | K47: New-hire productivity by month differs | L47: Not used by the four scenarios; used by later hiring and territory scenarios
A48: opps_won | B48: Qualified opportunities won, optional | C48: =IF('1) Data Entry'!E56="","",'1) Data Entry'!E56) | D48: =IF('1) Data Entry'!F56="","",'1) Data Entry'!F56) | F48: No estimate: enter a value or use the default | G48: ="" | H48: Optional; no default | I48: =IF(AND(D48="Use our estimate",E48<>""),E48,IF(C48<>"",C48,G48)) | J48: =IF(I48="","Not provided (optional)",IF(AND(D48="Use our estimate",E48<>""),"Our estimate",IF(C48<>"",IF(D48="Validated by Finance","Validated by Finance","Your entry (not validated)"),"Default (sample)"))) | L48: Estimate and check of close rate
A49: opps_lost | B49: Qualified opportunities lost, optional | C49: =IF('1) Data Entry'!E57="","",'1) Data Entry'!E57) | D49: =IF('1) Data Entry'!F57="","",'1) Data Entry'!F57) | F49: No estimate: enter a value or use the default | G49: ="" | H49: Optional; no default | I49: =IF(AND(D49="Use our estimate",E49<>""),E49,IF(C49<>"",C49,G49)) | J49: =IF(I49="","Not provided (optional)",IF(AND(D49="Use our estimate",E49<>""),"Our estimate",IF(C49<>"",IF(D49="Validated by Finance","Validated by Finance","Your entry (not validated)"),"Default (sample)"))) | L49: Estimate and check of close rate
A50: win_rate | B50: Close rate | C50: =IF('1) Data Entry'!E58="","",'1) Data Entry'!E58) | D50: =IF('1) Data Entry'!F58="","",'1) Data Entry'!F58) | E50: =IFERROR(IF(OR(v_opps_lost="",v_opps_won=""),"",v_opps_won/(v_opps_won+v_opps_lost)),"") | F50: Won ÷ (won + lost) | G50: 0.25 | H50: As-is model sample (illustrative) | I50: =IF(AND(D50="Use our estimate",E50<>""),E50,IF(C50<>"",C50,G50)) | J50: =IF(I50="","Not provided (optional)",IF(AND(D50="Use our estimate",E50<>""),"Our estimate",IF(C50<>"",IF(D50="Validated by Finance","Validated by Finance","Your entry (not validated)"),"Default (sample)"))) | K50: CRM won ÷ (won + lost) differs (close rate check) | L50: Every scenario: close rate
A51: cycle_months | B51: Sales cycle (months) | C51: =IF('1) Data Entry'!E59="","",'1) Data Entry'!E59) | D51: =IF('1) Data Entry'!F59="","",'1) Data Entry'!F59) | F51: No estimate: enter a value or use the default | G51: 6 | H51: As-is model sample (illustrative) | I51: =IF(AND(D51="Use our estimate",E51<>""),E51,IF(C51<>"",C51,G51)) | J51: =IF(I51="","Not provided (optional)",IF(AND(D51="Use our estimate",E51<>""),"Our estimate",IF(C51<>"",IF(D51="Validated by Finance","Validated by Finance","Your entry (not validated)"),"Default (sample)"))) | K51: CRM median cycle differs; Little's Law check fails | L51: Every scenario: cycle time
A52: deal_size | B52: Average revenue per contract | C52: =IF('1) Data Entry'!E60="","",'1) Data Entry'!E60) | D52: =IF('1) Data Entry'!F60="","",'1) Data Entry'!F60) | E52: =IFERROR(IF(OR(v_contracts="",v_revenue=""),"",v_revenue/v_contracts),"") | F52: Revenue ÷ contracts | G52: 75000 | H52: Reference value from another client, chosen so the model fits companies of any size (as-is model) | I52: =IF(AND(D52="Use our estimate",E52<>""),E52,IF(C52<>"",C52,G52)) | J52: =IF(I52="","Not provided (optional)",IF(AND(D52="Use our estimate",E52<>""),"Our estimate",IF(C52<>"",IF(D52="Validated by Finance","Validated by Finance","Your entry (not validated)"),"Default (sample)"))) | K52: Revenue ÷ contracts differs (deal size check) | L52: Every scenario: deal size
A53: open_opps_total | B53: Open qualified opportunities, optional | C53: =IF('1) Data Entry'!E61="","",'1) Data Entry'!E61) | D53: =IF('1) Data Entry'!F61="","",'1) Data Entry'!F61) | F53: No estimate: enter a value or use the default | G53: ="" | H53: Optional; no default | I53: =IF(AND(D53="Use our estimate",E53<>""),E53,IF(C53<>"",C53,G53)) | J53: =IF(I53="","Not provided (optional)",IF(AND(D53="Use our estimate",E53<>""),"Our estimate",IF(C53<>"",IF(D53="Validated by Finance","Validated by Finance","Your entry (not validated)"),"Default (sample)"))) | L53: Opportunities held per salesperson; Little's Law check
A54: opportunities_capacity | B54: Opportunities a salesperson can manage at once | C54: =IF('1) Data Entry'!E62="","",'1) Data Entry'!E62) | D54: =IF('1) Data Entry'!F62="","",'1) Data Entry'!F62) | F54: No estimate: enter a value or use the default | G54: 30 | H54: As-is model sample (illustrative) | I54: =IF(AND(D54="Use our estimate",E54<>""),E54,IF(C54<>"",C54,G54)) | J54: =IF(I54="","Not provided (optional)",IF(AND(D54="Use our estimate",E54<>""),"Our estimate",IF(C54<>"",IF(D54="Validated by Finance","Validated by Finance","Your entry (not validated)"),"Default (sample)"))) | K54: Close rate and cycle hold steady at loads above this level | L54: Every scenario: salesperson capacity
A58: Cross-checks: what the entries imply vs what was reported
A59: ID | B59: Check | C59: What it compares | D59: Model implies | E59: Reported / used | F59: Gap | G59: Tolerance | H59: Status | I59: Rule
A60: deal | B60: Deal size | C60: Revenue ÷ contracts, compared with the deal size used | D60: =IFERROR(IF(OR(v_revenue="",N(v_contracts)=0),"",v_revenue/v_contracts),"") | E60: =IFERROR(v_deal_size,"") | F60: =IF(OR(D60="",E60="",N(E60)=0),"",D60/E60-1) | G60: 0.1 | H60: =IF(F60="","NEEDS DATA",IF(ABS(F60)<=G60+1E-9,"PASS","REVIEW")) | I60: Gap = implied ÷ reported − 1. PASS if |gap| ≤ tolerance.
A61: revenue | B61: Revenue | C61: Revenue the model produces at baseline, compared with revenue reported | D61: =IFERROR(m_base_revenue,"") | E61: =IFERROR(v_revenue,"") | F61: =IF(OR(D61="",E61="",N(E61)=0),"",D61/E61-1) | G61: 0.1 | H61: =IF(F61="","NEEDS DATA",IF(ABS(F61)<=G61+1E-9,"PASS","REVIEW")) | I61: Gap = implied ÷ reported − 1. PASS if |gap| ≤ tolerance.
A62: contracts | B62: Contracts | C62: Contracts the model produces at baseline, compared with contracts reported | D62: =IFERROR(m_base_contracts,"") | E62: =IFERROR(v_contracts,"") | F62: =IF(OR(D62="",E62="",N(E62)=0),"",D62/E62-1) | G62: 0.1 | H62: =IF(F62="","NEEDS DATA",IF(ABS(F62)<=G62+1E-9,"PASS","REVIEW")) | I62: Gap = implied ÷ reported − 1. PASS if |gap| ≤ tolerance.
A63: win | B63: Close rate | C63: CRM won ÷ (won + lost), compared with the close rate used | D63: =IFERROR(IF(OR(v_opps_won="",v_opps_lost=""),"",v_opps_won/(v_opps_won+v_opps_lost)),"") | E63: =IFERROR(v_win_rate,"") | F63: =IF(OR(D63="",E63="",N(E63)=0),"",D63/E63-1) | G63: 0.1 | H63: =IF(F63="","NEEDS DATA",IF(ABS(F63)<=G63+1E-9,"PASS","REVIEW")) | I63: Gap = implied ÷ reported − 1. PASS if |gap| ≤ tolerance.
A64: commission | B64: Commission | C64: Commissions paid ÷ revenue, compared with the commission rate used | D64: =IFERROR(IF(OR(v_commissions_paid="",N(v_revenue)=0),"",v_commissions_paid/v_revenue),"") | E64: =IFERROR(v_commission_rate,"") | F64: =IF(OR(D64="",E64="",N(E64)=0),"",D64/E64-1) | G64: 0.1 | H64: =IF(F64="","NEEDS DATA",IF(ABS(F64)<=G64+1E-9,"PASS","REVIEW")) | I64: Gap = implied ÷ reported − 1. PASS if |gap| ≤ tolerance.
A65: littles | B65: Little's Law | C65: Opportunities each salesperson must hold to close the reported contracts (contracts ÷ close rate ÷ salespeople × cycle ÷ 12), compared with opportunities held in the CRM | D65: =IFERROR(IF(OR(N(v_win_rate)=0,N(v_filled_seats)=0),"",v_contracts/v_win_rate/v_filled_seats*v_cycle_months/12),"") | E65: =IFERROR(IF(N(v_open_opps_total)=0,"",v_open_opps_total/v_filled_seats),"") | F65: =IF(OR(D65="",E65="",N(E65)=0),"",D65/E65-1) | G65: 0.25 | H65: =IF(F65="","NEEDS DATA",IF(ABS(F65)<=G65+1E-9,"PASS","REVIEW")) | I65: Gap = implied ÷ reported − 1. PASS if |gap| ≤ tolerance.
A66: territory | B66: Territories | C66: Salespeople + open territories, compared with funded territories (runs only when the salesperson count is entered, not estimated) | D66: =IFERROR(IF('1) Data Entry'!$E$53="","",v_filled_seats+v_open_territories),"") | E66: =IFERROR(v_territory_count,"") | F66: =IF(OR(D66="",E66="",N(E66)=0),"",D66/E66-1) | G66: 0 | H66: =IF(F66="","NEEDS DATA",IF(ABS(F66)<=G66+1E-9,"PASS","REVIEW")) | I66: Gap = implied ÷ reported − 1. PASS if |gap| ≤ tolerance.
A69: Status
A70: st_required | B70: Entries the model uses (not optional blanks) | C70: =COUNTA($J$8:$J$54)-COUNTIF($J$8:$J$54,"Not provided*")
A71: st_validated | B71: Of those, validated by Finance | C71: =COUNTIF($J$8:$J$54,"Validated by Finance")
A72: st_review | B72: Checks needing review | C72: =COUNTIF($H$60:$H$66,"REVIEW")
A73: v_banner | B73: Banner shown on every client sheet | C73: =IF(AND(st_validated=st_required,st_review=0),"Baseline validated by Finance","Working model: not validated by Finance · "&st_validated&" of "&st_required&" entries validated · "&st_review&" checks need review")

Sheet 2) What-If
B1: 2) What-If Scenarios
B2: © 2000–2026 Growth Enablement. All rights reserved.
B3: =v_banner
B4: =IF(m_base_revenue="","",IF(ABS(m_base_revenue/v_revenue-1)<=0.1,"Calibration: the model baseline reproduces reported revenue within 10%.","Calibration: the model baseline produces "&TEXT(m_base_revenue,"$#,##0")&" of revenue; you reported "&TEXT(v_revenue,"$#,##0")&". Resolve the checks on 1) Data Entry before relying on these results."))
B6: Choose
B7: Scenario to show | C7: Combined | D7: Close rate, Cycle time, Deal size, or Combined (all three)
B8: Close rate improvement | C8: 0.1 | D8: Relative: 10% turns a 25% close rate into 27.5%
B9: Cycle time reduction | C9: 0.1 | D9: Relative: 10% turns 6 months into 5.4
B10: Deal size increase | C10: 0.1 | D10: Relative: 10% turns $75,000 into $82,500
B11: Target operating income (optional) | D11: Shows what each lever would have to achieve, at the bottom of this sheet
B13: The four scenarios at a glance
B14: Scenario | C14: Revenue | D14: Operating income | E14: Change in operating income | F14: Operating margin | G14: Guardrail
B15: Baseline | C15: ='2) What-If Logic'!C25 | D15: ='2) What-If Logic'!C38 | F15: ='2) What-If Logic'!C39 | G15: ='2) What-If Logic'!C50
B16: Close rate | C16: ='2) What-If Logic'!D25 | D16: ='2) What-If Logic'!D38 | E16: ='2) What-If Logic'!D44 | F16: ='2) What-If Logic'!D39 | G16: ='2) What-If Logic'!D50
B17: Cycle time | C17: ='2) What-If Logic'!E25 | D17: ='2) What-If Logic'!E38 | E17: ='2) What-If Logic'!E44 | F17: ='2) What-If Logic'!E39 | G17: ='2) What-If Logic'!E50
B18: Deal size | C18: ='2) What-If Logic'!F25 | D18: ='2) What-If Logic'!F38 | E18: ='2) What-If Logic'!F44 | F18: ='2) What-If Logic'!F39 | G18: ='2) What-If Logic'!F50
B19: Combined | C19: ='2) What-If Logic'!G25 | D19: ='2) What-If Logic'!G38 | E19: ='2) What-If Logic'!G44 | F19: ='2) What-If Logic'!G39 | G19: ='2) What-If Logic'!G50
B21: ="Pro forma income statement: "&wi_select
C22: Baseline | D22: =wi_select | E22: Change | F22: Change %
B23: Revenue | C23: ='2) What-If Logic'!C25 | D23: ='2) What-If Logic'!H25 | E23: =D23-C23 | F23: =IF(C23=0,"",(D23-C23)/ABS(C23))
B24: Cost of revenue | C24: ='2) What-If Logic'!C26 | D24: ='2) What-If Logic'!H26 | E24: =D24-C24 | F24: =IF(C24=0,"",(D24-C24)/ABS(C24))
B25: Gross profit | C25: ='2) What-If Logic'!C27 | D25: ='2) What-If Logic'!H27 | E25: =D25-C25 | F25: =IF(C25=0,"",(D25-C25)/ABS(C25))
B26: Research and development | C26: ='2) What-If Logic'!C28 | D26: ='2) What-If Logic'!H28 | E26: =D26-C26 | F26: =IF(C26=0,"",(D26-C26)/ABS(C26))
B27: Salesperson pay (salary and benefits) | C27: ='2) What-If Logic'!C29 | D27: ='2) What-If Logic'!H29 | E27: =D27-C27 | F27: =IF(C27=0,"",(D27-C27)/ABS(C27))
B28: Salesperson travel | C28: ='2) What-If Logic'!C30 | D28: ='2) What-If Logic'!H30 | E28: =D28-C28 | F28: =IF(C28=0,"",(D28-C28)/ABS(C28))
B29: Commissions | C29: ='2) What-If Logic'!C31 | D29: ='2) What-If Logic'!H31 | E29: =D29-C29 | F29: =IF(C29=0,"",(D29-C29)/ABS(C29))
B30: Sales overhead | C30: ='2) What-If Logic'!C32 | D30: ='2) What-If Logic'!H32 | E30: =D30-C30 | F30: =IF(C30=0,"",(D30-C30)/ABS(C30))
B31: Total sales costs | C31: ='2) What-If Logic'!C33 | D31: ='2) What-If Logic'!H33 | E31: =D31-C31 | F31: =IF(C31=0,"",(D31-C31)/ABS(C31))
B32: Marketing | C32: ='2) What-If Logic'!C34 | D32: ='2) What-If Logic'!H34 | E32: =D32-C32 | F32: =IF(C32=0,"",(D32-C32)/ABS(C32))
B33: Total sales and marketing | C33: ='2) What-If Logic'!C35 | D33: ='2) What-If Logic'!H35 | E33: =D33-C33 | F33: =IF(C33=0,"",(D33-C33)/ABS(C33))
B34: General and administrative | C34: ='2) What-If Logic'!C36 | D34: ='2) What-If Logic'!H36 | E34: =D34-C34 | F34: =IF(C34=0,"",(D34-C34)/ABS(C34))
... B36: Operating income | C36: ='2) What-If Logic'!C38 | D36: ='2) What-If Logic'!H38 | E36: =D36-C36 | F36: =IF(C36=0,"",(D36-C36)/ABS(C36))
B37: Operating margin | C37: ='2) What-If Logic'!C39 | D37: ='2) What-If Logic'!H39 | E37: =(D37-C37)*100
B38: True-up (change in revenue − change in costs − change in operating income) | D38: ='2) What-If Logic'!H46
B40: What drives it
C41: Baseline | D41: =wi_select | E41: Change
B42: Salespeople | C42: ='2) What-If Logic'!C12 | D42: ='2) What-If Logic'!H12 | E42: =IF(OR(C42="",D42=""),"",D42-C42)
B43: Opportunities worked at once, per salesperson | C43: ='2) What-If Logic'!C15 | D43: ='2) What-If Logic'!H15 | E43: =IF(OR(C43="",D43=""),"",D43-C43)
B44: Utilization of capacity (blank if pipeline not entered) | C44: ='2) What-If Logic'!C16 | D44: ='2) What-If Logic'!H16 | E44: =IF(OR(C44="",D44=""),"",D44-C44)
B45: Sales cycle (months) | C45: ='2) What-If Logic'!C17 | D45: ='2) What-If Logic'!H17 | E45: =IF(OR(C45="",D45=""),"",D45-C45)
B46: Opportunities resolved per salesperson per year | C46: ='2) What-If Logic'!C18 | D46: ='2) What-If Logic'!H18 | E46: =IF(OR(C46="",D46=""),"",D46-C46)
B47: Close rate | C47: ='2) What-If Logic'!C19 | D47: ='2) What-If Logic'!H19 | E47: =IF(OR(C47="",D47=""),"",D47-C47)
B48: Contracts per salesperson per year | C48: ='2) What-If Logic'!C20 | D48: ='2) What-If Logic'!H20 | E48: =IF(OR(C48="",D48=""),"",D48-C48)
B49: Average revenue per contract | C49: ='2) What-If Logic'!C21 | D49: ='2) What-If Logic'!H21 | E49: =IF(OR(C49="",D49=""),"",D49-C49)
B50: Revenue per salesperson | C50: ='2) What-If Logic'!C22 | D50: ='2) What-If Logic'!H22 | E50: =IF(OR(C50="",D50=""),"",D50-C50)
B51: Contracts | C51: ='2) What-If Logic'!C23 | D51: ='2) What-If Logic'!H23 | E51: =IF(OR(C51="",D51=""),"",D51-C51)
B52: ='2) What-If Logic'!H50
B54: What it would take to reach your target operating income
B55: The income statement is the constraint: an improvement only counts if it reaches operating income. Enter a target above, and the model works back to the revenue required and what each lever would have to achieve.
B56: Target operating income | C56: ='2) What-If Logic'!C54 | D56: ='2) What-If Logic'!C38 | E56: baseline
B57: Revenue required | C57: ='2) What-If Logic'!C58 | D57: ='2) What-If Logic'!C25 | E57: baseline
B58: Revenue increase required | C58: ='2) What-If Logic'!C59
B59: Close rate needed, if close rate alone | C59: ='2) What-If Logic'!C60 | D59: ='2) What-If Logic'!C19 | E59: baseline
B60: Cycle needed (months), if cycle alone | C60: ='2) What-If Logic'!C61 | D60: ='2) What-If Logic'!C17 | E60: baseline
B61: Deal size needed, if deal size alone | C61: ='2) What-If Logic'!C62 | D61: ='2) What-If Logic'!C21 | E61: baseline
B62: Or: improve close rate, cycle and deal size each by | C62: ='2) What-If Logic'!C63
B63: ='2) What-If Logic'!C64

Sheet 2) What-If Logic
A1: 2) What-If Logic
A2: Programming logic for the scenarios. Reads tab 1 only through the v_ names; reads 2) What-If only for the scenario choice, improvement sizes and target.
A3: Each row is one calculation. Column B states the rule in words; columns C–G apply it to the baseline and the four scenarios; column H shows the scenario chosen on 2) What-If.
A6: Line | B6: How it is calculated | C6: Baseline | D6: Close rate | E6: Cycle time | F6: Deal size | G6: Combined | H6: Selected scenario
A7: Scenario changes (set on 2) What-If)
A8: Close rate improvement | B8: Set on 2) What-If; applies to Close rate and Combined | C8: =0 | D8: =wi_win | E8: =0 | F8: =0 | G8: =wi_win | H8: =INDEX(C8:G8,MATCH(wi_select,$C$6:$G$6,0))
A9: Cycle time reduction | B9: Set on 2) What-If; applies to Cycle time and Combined | C9: =0 | D9: =0 | E9: =wi_cycle | F9: =0 | G9: =wi_cycle | H9: =INDEX(C9:G9,MATCH(wi_select,$C$6:$G$6,0))
A10: Deal size increase | B10: Set on 2) What-If; applies to Deal size and Combined | C10: =0 | D10: =0 | E10: =0 | F10: =wi_deal | G10: =wi_deal | H10: =INDEX(C10:G10,MATCH(wi_select,$C$6:$G$6,0))
A11: Salesperson throughput
A12: Salespeople | B12: Value used: quota-carrying salespeople | C12: =v_filled_seats | D12: =v_filled_seats | E12: =v_filled_seats | F12: =v_filled_seats | G12: =v_filled_seats | H12: =INDEX(C12:G12,MATCH(wi_select,$C$6:$G$6,0))
A13: Opportunities a salesperson can manage at once | B13: Value used: capacity | C13: =v_opportunities_capacity | D13: =v_opportunities_capacity | E13: =v_opportunities_capacity | F13: =v_opportunities_capacity | G13: =v_opportunities_capacity | H13: =INDEX(C13:G13,MATCH(wi_select,$C$6:$G$6,0))
A14: Opportunities each salesperson holds | B14: Open opportunities ÷ salespeople; blank if not entered | C14: =IF(N(v_open_opps_total)=0,"",v_open_opps_total/C12) | D14: =IF(N(v_open_opps_total)=0,"",v_open_opps_total/D12) | E14: =IF(N(v_open_opps_total)=0,"",v_open_opps_total/E12) | F14: =IF(N(v_open_opps_total)=0,"",v_open_opps_total/F12) | G14: =IF(N(v_open_opps_total)=0,"",v_open_opps_total/G12) | H14: =INDEX(C14:G14,MATCH(wi_select,$C$6:$G$6,0))
A15: Opportunities worked at once | B15: Lesser of held and capacity; capacity if held is not entered | C15: =IF(C14="",C13,MIN(C14,C13)) | D15: =IF(D14="",D13,MIN(D14,D13)) | E15: =IF(E14="",E13,MIN(E14,E13)) | F15: =IF(F14="",F13,MIN(F14,F13)) | G15: =IF(G14="",G13,MIN(G14,G13)) | H15: =INDEX(C15:G15,MATCH(wi_select,$C$6:$G$6,0))
A16: Utilization of capacity | B16: Worked ÷ capacity; blank if held is not entered | C16: =IF(C14="","",C15/C13) | D16: =IF(D14="","",D15/D13) | E16: =IF(E14="","",E15/E13) | F16: =IF(F14="","",F15/F13) | G16: =IF(G14="","",G15/G13) | H16: =INDEX(C16:G16,MATCH(wi_select,$C$6:$G$6,0))
A17: Sales cycle (months) | B17: Cycle used × (1 − cycle time reduction) | C17: =v_cycle_months*(1-C9) | D17: =v_cycle_months*(1-D9) | E17: =v_cycle_months*(1-E9) | F17: =v_cycle_months*(1-F9) | G17: =v_cycle_months*(1-G9) | H17: =INDEX(C17:G17,MATCH(wi_select,$C$6:$G$6,0))
A18: Opportunities resolved per salesperson per year | B18: Worked × 12 ÷ cycle (Little's Law) | C18: =C15*12/C17 | D18: =D15*12/D17 | E18: =E15*12/E17 | F18: =F15*12/F17 | G18: =G15*12/G17 | H18: =INDEX(C18:G18,MATCH(wi_select,$C$6:$G$6,0))
A19: Close rate | B19: Close rate used × (1 + close rate improvement) | C19: =v_win_rate*(1+C8) | D19: =v_win_rate*(1+D8) | E19: =v_win_rate*(1+E8) | F19: =v_win_rate*(1+F8) | G19: =v_win_rate*(1+G8) | H19: =INDEX(C19:G19,MATCH(wi_select,$C$6:$G$6,0))
A20: Contracts per salesperson per year | B20: Resolved × close rate | C20: =C18*C19 | D20: =D18*D19 | E20: =E18*E19 | F20: =F18*F19 | G20: =G18*G19 | H20: =INDEX(C20:G20,MATCH(wi_select,$C$6:$G$6,0))
A21: Average revenue per contract | B21: Deal size used × (1 + deal size increase) | C21: =v_deal_size*(1+C10) | D21: =v_deal_size*(1+D10) | E21: =v_deal_size*(1+E10) | F21: =v_deal_size*(1+F10) | G21: =v_deal_size*(1+G10) | H21: =INDEX(C21:G21,MATCH(wi_select,$C$6:$G$6,0))
A22: Revenue per salesperson | B22: Contracts per salesperson × deal size | C22: =C20*C21 | D22: =D20*D21 | E22: =E20*E21 | F22: =F20*F21 | G22: =G20*G21 | H22: =INDEX(C22:G22,MATCH(wi_select,$C$6:$G$6,0))
A23: Contracts | B23: Contracts per salesperson × salespeople | C23: =C20*C12 | D23: =D20*D12 | E23: =E20*E12 | F23: =F20*F12 | G23: =G20*G12 | H23: =INDEX(C23:G23,MATCH(wi_select,$C$6:$G$6,0))
A24: Pro forma income statement
A25: Revenue | B25: Revenue per salesperson × salespeople | C25: =C22*C12 | D25: =D22*D12 | E25: =E22*E12 | F25: =F22*F12 | G25: =G22*G12 | H25: =INDEX(C25:G25,MATCH(wi_select,$C$6:$G$6,0))
A26: Cost of revenue | B26: Revenue × cost of revenue % | C26: =C25*v_cost_of_revenue_pct | D26: =D25*v_cost_of_revenue_pct | E26: =E25*v_cost_of_revenue_pct | F26: =F25*v_cost_of_revenue_pct | G26: =G25*v_cost_of_revenue_pct | H26: =INDEX(C26:G26,MATCH(wi_select,$C$6:$G$6,0))
A27: Gross profit | B27: Revenue − cost of revenue | C27: =C25-C26 | D27: =D25-D26 | E27: =E25-E26 | F27: =F25-F26 | G27: =G25-G26 | H27: =INDEX(C27:G27,MATCH(wi_select,$C$6:$G$6,0))
A28: Research and development | B28: Revenue × R&D % | C28: =C25*v_rnd_pct | D28: =D25*v_rnd_pct | E28: =E25*v_rnd_pct | F28: =F25*v_rnd_pct | G28: =G25*v_rnd_pct | H28: =INDEX(C28:G28,MATCH(wi_select,$C$6:$G$6,0))
A29: Salesperson pay (salary and benefits) | B29: Fully loaded salary × salespeople | C29: =v_loaded_salary*C12 | D29: =v_loaded_salary*D12 | E29: =v_loaded_salary*E12 | F29: =v_loaded_salary*F12 | G29: =v_loaded_salary*G12 | H29: =INDEX(C29:G29,MATCH(wi_select,$C$6:$G$6,0))
A30: Salesperson travel | B30: Travel per salesperson × salespeople | C30: =v_travel_per_salesperson*C12 | D30: =v_travel_per_salesperson*D12 | E30: =v_travel_per_salesperson*E12 | F30: =v_travel_per_salesperson*F12 | G30: =v_travel_per_salesperson*G12 | H30: =INDEX(C30:G30,MATCH(wi_select,$C$6:$G$6,0))
A31: Commissions | B31: Commission rate × revenue | C31: =v_commission_rate*C25 | D31: =v_commission_rate*D25 | E31: =v_commission_rate*E25 | F31: =v_commission_rate*F25 | G31: =v_commission_rate*G25 | H31: =INDEX(C31:G31,MATCH(wi_select,$C$6:$G$6,0))
A32: Sales overhead | B32: Value used: sales overhead (fixed) | C32: =v_sales_overhead | D32: =v_sales_overhead | E32: =v_sales_overhead | F32: =v_sales_overhead | G32: =v_sales_overhead | H32: =INDEX(C32:G32,MATCH(wi_select,$C$6:$G$6,0))
A33: Total sales costs | B33: Pay + travel + commissions + overhead | C33: =C29+C30+C31+C32 | D33: =D29+D30+D31+D32 | E33: =E29+E30+E31+E32 | F33: =F29+F30+F31+F32 | G33: =G29+G30+G31+G32 | H33: =INDEX(C33:G33,MATCH(wi_select,$C$6:$G$6,0))
A34: Marketing | B34: Value used: marketing (fixed) | C34: =v_marketing | D34: =v_marketing | E34: =v_marketing | F34: =v_marketing | G34: =v_marketing | H34: =INDEX(C34:G34,MATCH(wi_select,$C$6:$G$6,0))
A35: Total sales and marketing | B35: Total sales costs + marketing | C35: =C33+C34 | D35: =D33+D34 | E35: =E33+E34 | F35: =F33+F34 | G35: =G33+G34 | H35: =INDEX(C35:G35,MATCH(wi_select,$C$6:$G$6,0))
A36: General and administrative | B36: Revenue × G&A % | C36: =C25*v_gna_pct | D36: =D25*v_gna_pct | E36: =E25*v_gna_pct | F36: =F25*v_gna_pct | G36: =G25*v_gna_pct | H36: =INDEX(C36:G36,MATCH(wi_select,$C$6:$G$6,0))
A37: Total operating expenses | B37: R&D + sales and marketing + G&A | C37: =C28+C35+C36 | D37: =D28+D35+D36 | E37: =E28+E35+E36 | F37: =F28+F35+F36 | G37: =G28+G35+G36 | H37: =INDEX(C37:G37,MATCH(wi_select,$C$6:$G$6,0))
A38: Operating income | B38: Gross profit − operating expenses | C38: =C27-C37 | D38: =D27-D37 | E38: =E27-E37 | F38: =F27-F37 | G38: =G27-G37 | H38: =INDEX(C38:G38,MATCH(wi_select,$C$6:$G$6,0))
A39: Operating margin | B39: Operating income ÷ revenue | C39: =IF(C25=0,"",C38/C25) | D39: =IF(D25=0,"",D38/D25) | E39: =IF(E25=0,"",E38/E25) | F39: =IF(F25=0,"",F38/F25) | G39: =IF(G25=0,"",G38/G25) | H39: =INDEX(C39:G39,MATCH(wi_select,$C$6:$G$6,0))
A40: Compared with baseline
A41: Total costs | B41: Cost of revenue + operating expenses | C41: =C26+C37 | D41: =D26+D37 | E41: =E26+E37 | F41: =F26+F37 | G41: =G26+G37 | H41: =INDEX(C41:G41,MATCH(wi_select,$C$6:$G$6,0))
A42: Change in revenue | B42: Revenue − baseline revenue | D42: =D25-$C$25 | E42: =E25-$C$25 | F42: =F25-$C$25 | G42: =G25-$C$25 | H42: =INDEX(C42:G42,MATCH(wi_select,$C$6:$G$6,0))
A43: Change in total costs | B43: Total costs − baseline total costs | D43: =D41-$C$41 | E43: =E41-$C$41 | F43: =F41-$C$41 | G43: =G41-$C$41 | H43: =INDEX(C43:G43,MATCH(wi_select,$C$6:$G$6,0))
A44: Change in operating income | B44: Operating income − baseline operating income | D44: =D38-$C$38 | E44: =E38-$C$38 | F44: =F38-$C$38 | G44: =G38-$C$38 | H44: =INDEX(C44:G44,MATCH(wi_select,$C$6:$G$6,0))
A45: Change in operating income, % | B45: Change ÷ baseline operating income | D45: =IF($C$38=0,"",D44/ABS($C$38)) | E45: =IF($C$38=0,"",E44/ABS($C$38)) | F45: =IF($C$38=0,"",F44/ABS($C$38)) | G45: =IF($C$38=0,"",G44/ABS($C$38)) | H45: =INDEX(C45:G45,MATCH(wi_select,$C$6:$G$6,0))
A46: True-up | B46: Change in revenue − change in costs − change in operating income = 0 | C46: — | D46: =IF(ABS(D42-D43-D44)<1,"Balanced","Check") | E46: =IF(ABS(E42-E43-E44)<1,"Balanced","Check") | F46: =IF(ABS(F42-F43-F44)<1,"Balanced","Check") | G46: =IF(ABS(G42-G43-G44)<1,"Balanced","Check") | H46: =INDEX(C46:G46,MATCH(wi_select,$C$6:$G$6,0))
A47: Percentage net gain (as-is definition) | B47: (Change in revenue − change in sales costs) ÷ baseline revenue | D47: =(D42-(D33-$C$33))/$C$25 | E47: =(E42-(E33-$C$33))/$C$25 | F47: =(F42-(F33-$C$33))/$C$25 | G47: =(G42-(G33-$C$33))/$C$25 | H47: =INDEX(C47:G47,MATCH(wi_select,$C$6:$G$6,0))
A48: Sales and marketing ROI | B48: (Revenue − sales and marketing) ÷ sales and marketing | C48: =IF(C35=0,"",(C25-C35)/C35) | D48: =IF(D35=0,"",(D25-D35)/D35) | E48: =IF(E35=0,"",(E25-E35)/E35) | F48: =IF(F35=0,"",(F25-F35)/F35) | G48: =IF(G35=0,"",(G25-G35)/G35) | H48: =INDEX(C48:G48,MATCH(wi_select,$C$6:$G$6,0))
A49: Guardrails
A50: Guardrail | B50: Close rate above 100%, cycle at or below zero, or pipeline (not capacity) limiting revenue | C50: =IF(C19>1,"Close rate above 100%: reduce the improvement",IF(C17<=0,"Cycle must stay above zero",IF(AND(C14<>"",N(C14)<C13),"Salespeople hold fewer opportunities than they can manage: the pipeline limits revenue","OK"))) | D50: =IF(D19>1,"Close rate above 100%: reduce the improvement",IF(D17<=0,"Cycle must stay above zero",IF(AND(D14<>"",N(D14)<D13),"Salespeople hold fewer opportunities than they can manage: the pipeline limits revenue","OK"))) | E50: =IF(E19>1,"Close rate above 100%: reduce the improvement",IF(E17<=0,"Cycle must stay above zero",IF(AND(E14<>"",N(E14)<E13),"Salespeople hold fewer opportunities than they can manage: the pipeline limits revenue","OK"))) | F50: =IF(F19>1,"Close rate above 100%: reduce the improvement",IF(F17<=0,"Cycle must stay above zero",IF(AND(F14<>"",N(F14)<F13),"Salespeople hold fewer opportunities than they can manage: the pipeline limits revenue","OK"))) | G50: =IF(G19>1,"Close rate above 100%: reduce the improvement",IF(G17<=0,"Cycle must stay above zero",IF(AND(G14<>"",N(G14)<G13),"Salespeople hold fewer opportunities than they can manage: the pipeline limits revenue","OK"))) | H50: =INDEX(C50:G50,MATCH(wi_select,$C$6:$G$6,0))
A52: Enabling constraint: what each lever would have to achieve to reach a target operating income
A53: Operating income = revenue × (1 − costs that move with revenue) − costs that do not. Revenue moves one for one with close rate and deal size, and inversely with cycle, so the revenue required converts directly into what each lever would need.
A54: Target operating income | B54: Entered on 2) What-If (optional) | C54: =IF(wi_target="","",wi_target)
A55: Costs that move with revenue, % of revenue | B55: Cost of revenue % + R&D % + G&A % + commission rate | C55: =v_cost_of_revenue_pct+v_rnd_pct+v_gna_pct+v_commission_rate
A56: Costs that do not move with revenue | B56: Baseline pay + travel + sales overhead + marketing | C56: =$C$29+$C$30+$C$32+$C$34
A57: Check: baseline operating income from this split | B57: Baseline revenue × (1 − variable %) − fixed; must equal baseline operating income | C57: =$C$25*(1-C55)-C56
A58: Revenue required | B58: (Target + fixed costs) ÷ (1 − variable %) | C58: =IF(C54="","",IF(C55>=1,"",(C54+C56)/(1-C55)))
A59: Revenue increase required | B59: Revenue required ÷ baseline revenue − 1 | C59: =IF(C58="","",C58/$C$25-1)
A60: Close rate needed (close rate alone) | B60: Close rate × (1 + increase); revenue moves one for one with close rate | C60: =IF(C59="","",v_win_rate*(1+C59))
A61: Cycle needed, months (cycle alone) | B61: Cycle ÷ (1 + increase); revenue moves inversely with cycle | C61: =IF(C59="","",v_cycle_months/(1+C59))
A62: Deal size needed (deal size alone) | B62: Deal size × (1 + increase) | C62: =IF(C59="","",v_deal_size*(1+C59))
A63: Combined: improvement needed in each of the three | B63: (1 + increase)^(1/3) − 1, if close rate, cycle and deal size each improve by the same share | C63: =IF(C59="","",IF(1+C59<=0,"",(1+C59)^(1/3)-1))
A64: Feasibility | B64: Flags a close rate above 100% or a target below baseline | C64: =IF(C59="","Enter a target operating income on 2) What-If",IF(C59<=0,"Target is at or below baseline operating income",IF(C60>1,"Close rate alone cannot reach the target (would exceed 100%)","Reachable in the model; test whether it is achievable")))
